{"name":"build-javascript","namedChunkGroups":{"polyfill":{"name":"polyfill","assets":[{"name":"webpack-runtime-52ba5158bed6284afb0b.js","size":3234},{"name":"polyfill-42203233a96ed73c2824.js","size":85830}],"filteredAssets":0,"assetsSize":89064,"filteredAuxiliaryAssets":2,"auxiliaryAssetsSize":221159},"app":{"name":"app","assets":[{"name":"webpack-runtime-52ba5158bed6284afb0b.js","size":3234},{"name":"framework-763b2637f9fc8a8dd99b.js","size":128698},{"name":"styles.6c65a383ea5c3ffdc198.css","size":263},{"name":"app-8df5ceb3309359f7aa7c.js","size":82518}],"filteredAssets":0,"assetsSize":214713,"filteredAuxiliaryAssets":3,"auxiliaryAssetsSize":722770},"component---src-pages-404-js":{"name":"component---src-pages-404-js","assets":[{"name":"component---src-pages-404-js-2d1feaaa6b0db5f9c0c8.js","size":744}],"filteredAssets":0,"assetsSize":744,"filteredAuxiliaryAssets":1,"auxiliaryAssetsSize":1839},"component---src-pages-index-tsx":{"name":"component---src-pages-index-tsx","assets":[{"name":"component---src-pages-index-tsx-61f765f52dc0575e32a0.js","size":13593}],"filteredAssets":0,"assetsSize":13593,"filteredAuxiliaryAssets":4,"auxiliaryAssetsSize":81051}},"assetsByChunkName":{"polyfill":["webpack-runtime-52ba5158bed6284afb0b.js","polyfill-42203233a96ed73c2824.js"],"app":["webpack-runtime-52ba5158bed6284afb0b.js","framework-763b2637f9fc8a8dd99b.js","styles.6c65a383ea5c3ffdc198.css","app-8df5ceb3309359f7aa7c.js"],"component---src-pages-404-js":["component---src-pages-404-js-2d1feaaa6b0db5f9c0c8.js"],"component---src-pages-index-tsx":["component---src-pages-index-tsx-61f765f52dc0575e32a0.js"]},"childAssetsByChunkName":{}}